Metadata-Version: 1.0
Name: starter.templates.python-django
Version: 0.1.0
Summary: Template for starter (http://github.com/klen/starter).
